markdown_link_attr_modifier.py
markdown_link_attr_modifier-0.2.1.dist-info/LICENSE
markdown_link_attr_modifier-0.2.1.dist-info/METADATA
markdown_link_attr_modifier-0.2.1.dist-info/WHEEL
markdown_link_attr_modifier-0.2.1.dist-info/top_level.txt
markdown_link_attr_modifier-0.2.1.dist-info/RECORD
